{"title":"Hexo博客导航栏menu无法跳转https","slug":"Hexo博客导航栏menu无法跳转https","date":"2019-03-05T04:08:12.000Z","updated":"2024-03-11T13:07:17.000Z","comments":true,"path":"api/articles/Hexo博客导航栏menu无法跳转https.json","excerpt":"Hexo博客部署到github&#x2F;coding后，点击菜单栏menu跳转至http而非https，提示找不到页面。","covers":null,"content":"<p>Hexo博客部署到github&#x2F;coding后，点击菜单栏menu跳转至http而非https，提示找不到页面。</p>\n<span id=\"more\"></span>\n<p>解决方案：</p>\n<p>修改主题配置文件“_config.yml”，在每一个menu的路径后面（url那一行）加一条正斜线，重新部署即可。</p>\n<figure class=\"highlight bash\"><table><tr><td class=\"gutter\"><pre><span class=\"line\">1</span><br><span class=\"line\">2</span><br><span class=\"line\">3</span><br><span class=\"line\">4</span><br><span class=\"line\">5</span><br><span class=\"line\">6</span><br><span class=\"line\">7</span><br><span class=\"line\">8</span><br><span class=\"line\">9</span><br><span class=\"line\">10</span><br><span class=\"line\">11</span><br><span class=\"line\">12</span><br><span class=\"line\">13</span><br><span class=\"line\">14</span><br><span class=\"line\">15</span><br><span class=\"line\">16</span><br><span class=\"line\">17</span><br><span class=\"line\">18</span><br><span class=\"line\">19</span><br><span class=\"line\">20</span><br><span class=\"line\">21</span><br><span class=\"line\">22</span><br><span class=\"line\">23</span><br><span class=\"line\">24</span><br><span class=\"line\">25</span><br><span class=\"line\">26</span><br><span class=\"line\">27</span><br><span class=\"line\">28</span><br><span class=\"line\">29</span><br><span class=\"line\">30</span><br><span class=\"line\">31</span><br><span class=\"line\">32</span><br><span class=\"line\">33</span><br><span class=\"line\">34</span><br><span class=\"line\">35</span><br><span class=\"line\">36</span><br><span class=\"line\">37</span><br><span class=\"line\">38</span><br><span class=\"line\">39</span><br><span class=\"line\">40</span><br><span class=\"line\">41</span><br><span class=\"line\">42</span><br><span class=\"line\">43</span><br><span class=\"line\">44</span><br><span class=\"line\">45</span><br><span class=\"line\">46</span><br><span class=\"line\">47</span><br><span class=\"line\">48</span><br><span class=\"line\">49</span><br></pre></td><td class=\"code\"><pre><span class=\"line\">menu:</span><br><span class=\"line\"></span><br><span class=\"line\"><span class=\"comment\"># index</span></span><br><span class=\"line\"></span><br><span class=\"line\">  - title: 首页</span><br><span class=\"line\"></span><br><span class=\"line\">    icon: home</span><br><span class=\"line\"></span><br><span class=\"line\">    url: /</span><br><span class=\"line\"></span><br><span class=\"line\">  <span class=\"comment\"># archives</span></span><br><span class=\"line\"></span><br><span class=\"line\">  - title: 归档</span><br><span class=\"line\"></span><br><span class=\"line\">    icon: archive</span><br><span class=\"line\"></span><br><span class=\"line\">    url: archives/</span><br><span class=\"line\"></span><br><span class=\"line\">  <span class=\"comment\"># categories</span></span><br><span class=\"line\"></span><br><span class=\"line\">  - title: 分类</span><br><span class=\"line\"></span><br><span class=\"line\">    icon: list</span><br><span class=\"line\"></span><br><span class=\"line\">    url: categories/</span><br><span class=\"line\"></span><br><span class=\"line\">  <span class=\"comment\"># tags</span></span><br><span class=\"line\"></span><br><span class=\"line\">  - title: 标签</span><br><span class=\"line\"></span><br><span class=\"line\">    icon: tags</span><br><span class=\"line\"></span><br><span class=\"line\">    url: tags/</span><br><span class=\"line\"></span><br><span class=\"line\">  <span class=\"comment\"># about</span></span><br><span class=\"line\"></span><br><span class=\"line\">  - title: 关于我</span><br><span class=\"line\"></span><br><span class=\"line\">    icon: user</span><br><span class=\"line\"></span><br><span class=\"line\">    url: /about/</span><br><span class=\"line\"></span><br><span class=\"line\">  <span class=\"comment\"># archives</span></span><br><span class=\"line\"></span><br><span class=\"line\">  - title: 留言板</span><br><span class=\"line\"></span><br><span class=\"line\">    icon: comments</span><br><span class=\"line\"></span><br><span class=\"line\">    url: Message/</span><br></pre></td></tr></table></figure>","more":"<p>解决方案：</p>\n<p>修改主题配置文件“_config.yml”，在每一个menu的路径后面（url那一行）加一条正斜线，重新部署即可。</p>\n<figure class=\"highlight bash\"><table><tr><td class=\"gutter\"><pre><span class=\"line\">1</span><br><span class=\"line\">2</span><br><span class=\"line\">3</span><br><span class=\"line\">4</span><br><span class=\"line\">5</span><br><span class=\"line\">6</span><br><span class=\"line\">7</span><br><span class=\"line\">8</span><br><span class=\"line\">9</span><br><span class=\"line\">10</span><br><span class=\"line\">11</span><br><span class=\"line\">12</span><br><span class=\"line\">13</span><br><span class=\"line\">14</span><br><span class=\"line\">15</span><br><span class=\"line\">16</span><br><span class=\"line\">17</span><br><span class=\"line\">18</span><br><span class=\"line\">19</span><br><span class=\"line\">20</span><br><span class=\"line\">21</span><br><span class=\"line\">22</span><br><span class=\"line\">23</span><br><span class=\"line\">24</span><br><span class=\"line\">25</span><br><span class=\"line\">26</span><br><span class=\"line\">27</span><br><span class=\"line\">28</span><br><span class=\"line\">29</span><br><span class=\"line\">30</span><br><span class=\"line\">31</span><br><span class=\"line\">32</span><br><span class=\"line\">33</span><br><span class=\"line\">34</span><br><span class=\"line\">35</span><br><span class=\"line\">36</span><br><span class=\"line\">37</span><br><span class=\"line\">38</span><br><span class=\"line\">39</span><br><span class=\"line\">40</span><br><span class=\"line\">41</span><br><span class=\"line\">42</span><br><span class=\"line\">43</span><br><span class=\"line\">44</span><br><span class=\"line\">45</span><br><span class=\"line\">46</span><br><span class=\"line\">47</span><br><span class=\"line\">48</span><br><span class=\"line\">49</span><br></pre></td><td class=\"code\"><pre><span class=\"line\">menu:</span><br><span class=\"line\"></span><br><span class=\"line\"><span class=\"comment\"># index</span></span><br><span class=\"line\"></span><br><span class=\"line\">  - title: 首页</span><br><span class=\"line\"></span><br><span class=\"line\">    icon: home</span><br><span class=\"line\"></span><br><span class=\"line\">    url: /</span><br><span class=\"line\"></span><br><span class=\"line\">  <span class=\"comment\"># archives</span></span><br><span class=\"line\"></span><br><span class=\"line\">  - title: 归档</span><br><span class=\"line\"></span><br><span class=\"line\">    icon: archive</span><br><span class=\"line\"></span><br><span class=\"line\">    url: archives/</span><br><span class=\"line\"></span><br><span class=\"line\">  <span class=\"comment\"># categories</span></span><br><span class=\"line\"></span><br><span class=\"line\">  - title: 分类</span><br><span class=\"line\"></span><br><span class=\"line\">    icon: list</span><br><span class=\"line\"></span><br><span class=\"line\">    url: categories/</span><br><span class=\"line\"></span><br><span class=\"line\">  <span class=\"comment\"># tags</span></span><br><span class=\"line\"></span><br><span class=\"line\">  - title: 标签</span><br><span class=\"line\"></span><br><span class=\"line\">    icon: tags</span><br><span class=\"line\"></span><br><span class=\"line\">    url: tags/</span><br><span class=\"line\"></span><br><span class=\"line\">  <span class=\"comment\"># about</span></span><br><span class=\"line\"></span><br><span class=\"line\">  - title: 关于我</span><br><span class=\"line\"></span><br><span class=\"line\">    icon: user</span><br><span class=\"line\"></span><br><span class=\"line\">    url: /about/</span><br><span class=\"line\"></span><br><span class=\"line\">  <span class=\"comment\"># archives</span></span><br><span class=\"line\"></span><br><span class=\"line\">  - title: 留言板</span><br><span class=\"line\"></span><br><span class=\"line\">    icon: comments</span><br><span class=\"line\"></span><br><span class=\"line\">    url: Message/</span><br></pre></td></tr></table></figure>","categories":[{"name":"网站建设","path":"api/categories/网站建设.json"}],"tags":[{"name":"Hexo","path":"api/tags/Hexo.json"}]}