{"title":"fengjing","date":"2022-01-11T00:48:34.000Z","updated":"2022-01-11T00:48:34.518Z","comments":true,"path":"api/pages/fengjing.json","covers":["https://cdn.jsdelivr.net/gh/liaochenlanruo/cdn@master/images/zipai/IMG_20210412_192425.jpg","https://cdn.jsdelivr.net/gh/liaochenlanruo/cdn@master/images/zipai/IMG_20190607_195648.jpg","https://cdn.jsdelivr.net/gh/liaochenlanruo/cdn@master/images/zipai/IMG_20200627_094055.jpg","https://cdn.jsdelivr.net/gh/liaochenlanruo/cdn@master/images/zipai/IMG_20210504_164143.jpg","https://cdn.jsdelivr.net/gh/liaochenlanruo/cdn@master/images/zipai/IMG_20190721_112738.jpg","https://cdn.jsdelivr.net/gh/liaochenlanruo/cdn@master/images/zipai/IMG_20210102_181731.jpg","https://cdn.jsdelivr.net/gh/liaochenlanruo/cdn@master/images/zipai/IMG_20210510_184640.jpg"],"excerpt":null,"content":"<div class=\"gallery \">\n              <p><img src=\"https://cdn.jsdelivr.net/gh/liaochenlanruo/cdn@master/images/zipai/IMG_20210412_192425.jpg\" class=\"lazyload placeholder\" data-srcset=\"https://cdn.jsdelivr.net/gh/liaochenlanruo/cdn@master/images/zipai/IMG_20210412_192425.jpg\" srcset=\"https://img2.baidu.com/it/u=2037979560,2772131037&fm=26&fmt=auto&gp=0.jpg\" alt=\"图片描述\" /><br /><img src=\"https://cdn.jsdelivr.net/gh/liaochenlanruo/cdn@master/images/zipai/IMG_20210504_114025.jpg\" class=\"lazyload placeholder\" data-srcset=\"https://cdn.jsdelivr.net/gh/liaochenlanruo/cdn@master/images/zipai/IMG_20210504_114025.jpg\" srcset=\"https://img2.baidu.com/it/u=2037979560,2772131037&fm=26&fmt=auto&gp=0.jpg\" alt=\"图片描述\" /><br /><img src=\"https://cdn.jsdelivr.net/gh/liaochenlanruo/cdn@master/images/zipai/IMG_20210523_221134.jpg\" class=\"lazyload placeholder\" data-srcset=\"https://cdn.jsdelivr.net/gh/liaochenlanruo/cdn@master/images/zipai/IMG_20210523_221134.jpg\" srcset=\"https://img2.baidu.com/it/u=2037979560,2772131037&fm=26&fmt=auto&gp=0.jpg\" alt=\"图片描述\" /><br /><img src=\"https://cdn.jsdelivr.net/gh/liaochenlanruo/cdn@master/images/zipai/IMG_20210504_191053.jpg\" class=\"lazyload placeholder\" data-srcset=\"https://cdn.jsdelivr.net/gh/liaochenlanruo/cdn@master/images/zipai/IMG_20210504_191053.jpg\" srcset=\"https://img2.baidu.com/it/u=2037979560,2772131037&fm=26&fmt=auto&gp=0.jpg\" alt=\"图片描述\" /></p>\n            </div>\n<div class=\"gallery \">\n              <p><img src=\"https://cdn.jsdelivr.net/gh/liaochenlanruo/cdn@master/images/zipai/IMG_20190607_195648.jpg\" class=\"lazyload placeholder\" data-srcset=\"https://cdn.jsdelivr.net/gh/liaochenlanruo/cdn@master/images/zipai/IMG_20190607_195648.jpg\" srcset=\"https://img2.baidu.com/it/u=2037979560,2772131037&fm=26&fmt=auto&gp=0.jpg\" alt=\"图片描述\" /><br /><img src=\"https://cdn.jsdelivr.net/gh/liaochenlanruo/cdn@master/images/zipai/IMG_20191122_165944.jpg\" class=\"lazyload placeholder\" data-srcset=\"https://cdn.jsdelivr.net/gh/liaochenlanruo/cdn@master/images/zipai/IMG_20191122_165944.jpg\" srcset=\"https://img2.baidu.com/it/u=2037979560,2772131037&fm=26&fmt=auto&gp=0.jpg\" alt=\"图片描述\" /></p>\n            </div>\n<div class=\"gallery \">\n              <p><img src=\"https://cdn.jsdelivr.net/gh/liaochenlanruo/cdn@master/images/zipai/IMG_20200627_094055.jpg\" class=\"lazyload placeholder\" data-srcset=\"https://cdn.jsdelivr.net/gh/liaochenlanruo/cdn@master/images/zipai/IMG_20200627_094055.jpg\" srcset=\"https://img2.baidu.com/it/u=2037979560,2772131037&fm=26&fmt=auto&gp=0.jpg\" alt=\"图片描述\" /><br /><img src=\"https://cdn.jsdelivr.net/gh/liaochenlanruo/cdn@master/images/zipai/IMG_20191121_145533.jpg\" class=\"lazyload placeholder\" data-srcset=\"https://cdn.jsdelivr.net/gh/liaochenlanruo/cdn@master/images/zipai/IMG_20191121_145533.jpg\" srcset=\"https://img2.baidu.com/it/u=2037979560,2772131037&fm=26&fmt=auto&gp=0.jpg\" alt=\"图片描述\" /><br /><img src=\"https://cdn.jsdelivr.net/gh/liaochenlanruo/cdn@master/images/zipai/IMG_20200627_094936.jpg\" class=\"lazyload placeholder\" data-srcset=\"https://cdn.jsdelivr.net/gh/liaochenlanruo/cdn@master/images/zipai/IMG_20200627_094936.jpg\" srcset=\"https://img2.baidu.com/it/u=2037979560,2772131037&fm=26&fmt=auto&gp=0.jpg\" alt=\"图片描述\" /></p>\n            </div>\n<div class=\"gallery \">\n              <p><img src=\"https://cdn.jsdelivr.net/gh/liaochenlanruo/cdn@master/images/zipai/IMG_20210504_164143.jpg\" class=\"lazyload placeholder\" data-srcset=\"https://cdn.jsdelivr.net/gh/liaochenlanruo/cdn@master/images/zipai/IMG_20210504_164143.jpg\" srcset=\"https://img2.baidu.com/it/u=2037979560,2772131037&fm=26&fmt=auto&gp=0.jpg\" alt=\"图片描述\" /><br /><img src=\"https://cdn.jsdelivr.net/gh/liaochenlanruo/cdn@master/images/zipai/IMG_20210504_190706.jpg\" class=\"lazyload placeholder\" data-srcset=\"https://cdn.jsdelivr.net/gh/liaochenlanruo/cdn@master/images/zipai/IMG_20210504_190706.jpg\" srcset=\"https://img2.baidu.com/it/u=2037979560,2772131037&fm=26&fmt=auto&gp=0.jpg\" alt=\"图片描述\" /><br /><img src=\"https://cdn.jsdelivr.net/gh/liaochenlanruo/cdn@master/images/zipai/IMG_20210504_191339.jpg\" class=\"lazyload placeholder\" data-srcset=\"https://cdn.jsdelivr.net/gh/liaochenlanruo/cdn@master/images/zipai/IMG_20210504_191339.jpg\" srcset=\"https://img2.baidu.com/it/u=2037979560,2772131037&fm=26&fmt=auto&gp=0.jpg\" alt=\"图片描述\" /><br /><img src=\"https://cdn.jsdelivr.net/gh/liaochenlanruo/cdn@master/images/zipai/IMG_20210504_191412.jpg\" class=\"lazyload placeholder\" data-srcset=\"https://cdn.jsdelivr.net/gh/liaochenlanruo/cdn@master/images/zipai/IMG_20210504_191412.jpg\" srcset=\"https://img2.baidu.com/it/u=2037979560,2772131037&fm=26&fmt=auto&gp=0.jpg\" alt=\"图片描述\" /></p>\n            </div>\n<div class=\"gallery \">\n              <p><img src=\"https://cdn.jsdelivr.net/gh/liaochenlanruo/cdn@master/images/zipai/IMG_20190721_112738.jpg\" class=\"lazyload placeholder\" data-srcset=\"https://cdn.jsdelivr.net/gh/liaochenlanruo/cdn@master/images/zipai/IMG_20190721_112738.jpg\" srcset=\"https://img2.baidu.com/it/u=2037979560,2772131037&fm=26&fmt=auto&gp=0.jpg\" alt=\"图片描述\" /><br /><img src=\"https://cdn.jsdelivr.net/gh/liaochenlanruo/cdn@master/images/zipai/IMG_20190721_113754.jpg\" class=\"lazyload placeholder\" data-srcset=\"https://cdn.jsdelivr.net/gh/liaochenlanruo/cdn@master/images/zipai/IMG_20190721_113754.jpg\" srcset=\"https://img2.baidu.com/it/u=2037979560,2772131037&fm=26&fmt=auto&gp=0.jpg\" alt=\"图片描述\" /><br /><img src=\"https://cdn.jsdelivr.net/gh/liaochenlanruo/cdn@master/images/zipai/IMG_20190721_143007.jpg\" class=\"lazyload placeholder\" data-srcset=\"https://cdn.jsdelivr.net/gh/liaochenlanruo/cdn@master/images/zipai/IMG_20190721_143007.jpg\" srcset=\"https://img2.baidu.com/it/u=2037979560,2772131037&fm=26&fmt=auto&gp=0.jpg\" alt=\"图片描述\" /></p>\n            </div>\n<div class=\"gallery \">\n              <p><img src=\"https://cdn.jsdelivr.net/gh/liaochenlanruo/cdn@master/images/zipai/IMG_20210102_181731.jpg\" class=\"lazyload placeholder\" data-srcset=\"https://cdn.jsdelivr.net/gh/liaochenlanruo/cdn@master/images/zipai/IMG_20210102_181731.jpg\" srcset=\"https://img2.baidu.com/it/u=2037979560,2772131037&fm=26&fmt=auto&gp=0.jpg\" alt=\"图片描述\" /><br /><img src=\"https://cdn.jsdelivr.net/gh/liaochenlanruo/cdn@master/images/zipai/IMG_20190607_195914.jpg\" class=\"lazyload placeholder\" data-srcset=\"https://cdn.jsdelivr.net/gh/liaochenlanruo/cdn@master/images/zipai/IMG_20190607_195914.jpg\" srcset=\"https://img2.baidu.com/it/u=2037979560,2772131037&fm=26&fmt=auto&gp=0.jpg\" alt=\"图片描述\" /></p>\n            </div>\n<div class=\"gallery \">\n              <p><img src=\"https://cdn.jsdelivr.net/gh/liaochenlanruo/cdn@master/images/zipai/IMG_20210510_184640.jpg\" class=\"lazyload placeholder\" data-srcset=\"https://cdn.jsdelivr.net/gh/liaochenlanruo/cdn@master/images/zipai/IMG_20210510_184640.jpg\" srcset=\"https://img2.baidu.com/it/u=2037979560,2772131037&fm=26&fmt=auto&gp=0.jpg\" alt=\"图片描述\" /><br /><img src=\"https://cdn.jsdelivr.net/gh/liaochenlanruo/cdn@master/images/zipai/IMG_20210512_184947.jpg\" class=\"lazyload placeholder\" data-srcset=\"https://cdn.jsdelivr.net/gh/liaochenlanruo/cdn@master/images/zipai/IMG_20210512_184947.jpg\" srcset=\"https://img2.baidu.com/it/u=2037979560,2772131037&fm=26&fmt=auto&gp=0.jpg\" alt=\"图片描述\" /><br /><img src=\"https://cdn.jsdelivr.net/gh/liaochenlanruo/cdn@master/images/zipai/IMG_20210525_084934.jpg\" class=\"lazyload placeholder\" data-srcset=\"https://cdn.jsdelivr.net/gh/liaochenlanruo/cdn@master/images/zipai/IMG_20210525_084934.jpg\" srcset=\"https://img2.baidu.com/it/u=2037979560,2772131037&fm=26&fmt=auto&gp=0.jpg\" alt=\"图片描述\" /></p>\n            </div>"}